{"total_sentiment_rank":1.3333333333333333,"in_reply_to_status_id_str":null,"in_reply_to_status_id":null,"emojiList":null,"created_at":"Sat Feb 27 15:01:43 +0000 2016","in_reply_to_user_id_str":null,"source":"<a href=\"http:\/\/twitter.com\" rel=\"nofollow\">Twitter Web Client<\/a>","retweeted_status":{"in_reply_to_status_id_str":null,"in_reply_to_status_id":null,"created_at":"Sat Feb 27 14:57:46 +0000 2016","in_reply_to_user_id_str":null,"source":"<a href=\"http:\/\/www.handmark.com\" rel=\"nofollow\">TweetCaster for iOS<\/a>","retweet_count":1,"retweeted":false,"geo":null,"filter_level":"low","in_reply_to_screen_name":null,"is_quote_status":false,"id_str":"703594881491431424","in_reply_to_user_id":null,"favorite_count":0,"id":703594881491431424,"text":"2\/27 GAMEDAY News Links! https:\/\/t.co\/yWmq8mf1gm Is today the day? #kubball #Big12Champs12Straight #kansas #jayhawks vs #wreckem for the win","place":null,"lang":"en","favorited":false,"possibly_sensitive":false,"coordinates":null,"truncated":false,"entities":{"urls":[{"display_url":"collegehoophits.com","indices":[25,48],"expanded_url":"http:\/\/collegehoophits.com","url":"https:\/\/t.co\/yWmq8mf1gm"}],"hashtags":[{"indices":[67,75],"text":"kubball"},{"indices":[76,98],"text":"Big12Champs12Straight"},{"indices":[99,106],"text":"kansas"},{"indices":[107,116],"text":"jayhawks"},{"indices":[120,128],"text":"wreckem"}],"user_mentions":[],"symbols":[]},"contributors":null,"user":{"utc_offset":-21600,"friends_count":0,"profile_image_url_https":"https:\/\/pbs.twimg.com\/profile_images\/1781191188\/championship_ring_normal.jpg","listed_count":7,"profile_background_image_url":"http:\/\/abs.twimg.com\/images\/themes\/theme14\/bg.gif","default_profile_image":false,"favourites_count":0,"description":null,"created_at":"Wed Jan 25 21:55:37 +0000 2012","is_translator":false,"profile_background_image_url_https":"https:\/\/abs.twimg.com\/images\/themes\/theme14\/bg.gif","protected":false,"screen_name":"CollegeHoopHits","id_str":"474329899","profile_link_color":"009999","id":474329899,"geo_enabled":false,"profile_background_color":"131516","lang":"en","profile_sidebar_border_color":"EEEEEE","profile_text_color":"333333","verified":false,"profile_image_url":"http:\/\/pbs.twimg.com\/profile_images\/1781191188\/championship_ring_normal.jpg","time_zone":"Central Time (US & Canada)","url":"http:\/\/www.collegehoophits.com","contributors_enabled":false,"profile_background_tile":true,"statuses_count":1092,"follow_request_sent":null,"followers_count":80,"profile_use_background_image":true,"default_profile":false,"following":null,"name":"College Hoop Hits","location":null,"profile_sidebar_fill_color":"EFEFEF","notifications":null}},"retweet_count":0,"retweeted":false,"geo":null,"filter_level":"low","in_reply_to_screen_name":null,"is_quote_status":false,"id_str":"703595874706812928","text_sentiment_rank":1.3333333333333333,"in_reply_to_user_id":null,"favorite_count":0,"id":703595874706812928,"text":"RT @CollegeHoopHits: 2\/27 GAMEDAY News Links! https:\/\/t.co\/yWmq8mf1gm Is today the day? #kubball #Big12Champs12Straight #kansas #jayhawks v\u2026","place":null,"lang":"en","favorited":false,"possibly_sensitive":false,"emoji_sentiment_rank_str":null,"coordinates":null,"truncated":false,"timestamp_ms":"1456585303366","entities":{"urls":[{"display_url":"collegehoophits.com","indices":[46,69],"expanded_url":"http:\/\/collegehoophits.com","url":"https:\/\/t.co\/yWmq8mf1gm"}],"hashtags":[{"indices":[88,96],"text":"kubball"},{"indices":[97,119],"text":"Big12Champs12Straight"},{"indices":[120,127],"text":"kansas"},{"indices":[128,137],"text":"jayhawks"},{"indices":[139,140],"text":"wreckem"}],"user_mentions":[{"indices":[3,19],"screen_name":"CollegeHoopHits","id_str":"474329899","name":"College Hoop Hits","id":474329899}],"symbols":[]},"total_sentiment_rank_str":"1.3333333333333333","text_sentiment_rank_str":"1.3333333333333333","contributors":null,"emoji_sentiment_rank":null,"user":{"utc_offset":-21600,"friends_count":341,"profile_image_url_https":"https:\/\/pbs.twimg.com\/profile_images\/2134967961\/theshotcolorlightgz1_normal.jpg","listed_count":9,"profile_background_image_url":"http:\/\/abs.twimg.com\/images\/themes\/theme9\/bg.gif","default_profile_image":false,"favourites_count":102,"description":null,"created_at":"Wed Mar 11 19:50:58 +0000 2009","is_translator":false,"profile_background_image_url_https":"https:\/\/abs.twimg.com\/images\/themes\/theme9\/bg.gif","protected":false,"screen_name":"kcjc1","id_str":"23816831","profile_link_color":"2FC2EF","id":23816831,"geo_enabled":false,"profile_background_color":"1A1B1F","lang":"en","profile_sidebar_border_color":"181A1E","profile_text_color":"666666","verified":false,"profile_image_url":"http:\/\/pbs.twimg.com\/profile_images\/2134967961\/theshotcolorlightgz1_normal.jpg","time_zone":"Central Time (US & Canada)","url":null,"contributors_enabled":false,"profile_background_tile":false,"statuses_count":3297,"follow_request_sent":null,"followers_count":118,"profile_use_background_image":true,"default_profile":false,"following":null,"name":"kcjc","location":null,"profile_sidebar_fill_color":"252429","notifications":null}}