{"total_sentiment_rank":2.0,"in_reply_to_status_id_str":null,"in_reply_to_status_id":null,"emojiList":null,"created_at":"Mon Feb 22 18:57:33 +0000 2016","in_reply_to_user_id_str":null,"source":"<a href=\"http:\/\/twitter.com\/download\/android\" rel=\"nofollow\">Twitter for Android<\/a>","retweeted_status":{"in_reply_to_status_id_str":null,"in_reply_to_status_id":null,"coordinates":null,"created_at":"Mon Feb 22 18:53:59 +0000 2016","truncated":false,"in_reply_to_user_id_str":null,"source":"<a href=\"http:\/\/twitter.com\" rel=\"nofollow\">Twitter Web Client<\/a>","retweet_count":2,"retweeted":false,"geo":null,"filter_level":"low","in_reply_to_screen_name":null,"is_quote_status":false,"entities":{"urls":[],"hashtags":[{"indices":[25,35],"text":"TexasTech"}],"user_mentions":[],"symbols":[]},"id_str":"701842389355229185","in_reply_to_user_id":null,"favorite_count":1,"id":701842389355229185,"text":"Wow, somehow AP respects #TexasTech enough to keep OU in the third spot after losing to us, but not enough to put us in the Top 25.","place":null,"contributors":null,"lang":"en","user":{"utc_offset":-21600,"friends_count":97,"profile_image_url_https":"https:\/\/pbs.twimg.com\/profile_images\/676485613416124416\/BD4t3c4R_normal.png","listed_count":4,"profile_background_image_url":"http:\/\/abs.twimg.com\/images\/themes\/theme14\/bg.gif","default_profile_image":false,"favourites_count":6092,"description":"Sun's up, Guns up! All things Texas Tech sports!","created_at":"Wed Mar 11 18:19:24 +0000 2009","is_translator":false,"profile_background_image_url_https":"https:\/\/abs.twimg.com\/images\/themes\/theme14\/bg.gif","protected":false,"screen_name":"gunsupnation","id_str":"23802398","profile_link_color":"000000","id":23802398,"geo_enabled":true,"profile_background_color":"131516","lang":"en","profile_sidebar_border_color":"EEEEEE","profile_text_color":"333333","verified":false,"profile_image_url":"http:\/\/pbs.twimg.com\/profile_images\/676485613416124416\/BD4t3c4R_normal.png","time_zone":"Central Time (US & Canada)","url":"http:\/\/gunsupnation.com","contributors_enabled":false,"profile_background_tile":true,"profile_banner_url":"https:\/\/pbs.twimg.com\/profile_banners\/23802398\/1450123407","statuses_count":1522,"follow_request_sent":null,"followers_count":182,"profile_use_background_image":true,"default_profile":false,"following":null,"name":"Guns Up Nation","location":"Red Raider Land","profile_sidebar_fill_color":"EFEFEF","notifications":null},"favorited":false},"retweet_count":0,"retweeted":false,"geo":null,"filter_level":"low","in_reply_to_screen_name":null,"is_quote_status":false,"id_str":"701843284033798144","text_sentiment_rank":2.0,"in_reply_to_user_id":null,"favorite_count":0,"id":701843284033798144,"text":"RT @gunsupnation: Wow, somehow AP respects #TexasTech enough to keep OU in the third spot after losing to us, but not enough to put us in t\u2026","place":null,"lang":"en","favorited":false,"emoji_sentiment_rank_str":null,"coordinates":null,"truncated":false,"timestamp_ms":"1456167453188","entities":{"urls":[],"hashtags":[{"indices":[43,53],"text":"TexasTech"}],"user_mentions":[{"indices":[3,16],"screen_name":"gunsupnation","id_str":"23802398","name":"Guns Up Nation","id":23802398}],"symbols":[]},"total_sentiment_rank_str":"2.0","text_sentiment_rank_str":"2.0","contributors":null,"emoji_sentiment_rank":null,"user":{"utc_offset":-21600,"friends_count":282,"profile_image_url_https":"https:\/\/pbs.twimg.com\/profile_images\/497799795361079296\/dCapztJV_normal.jpeg","listed_count":1,"profile_background_image_url":"http:\/\/pbs.twimg.com\/profile_background_images\/625129012\/classic-rock.jpg","default_profile_image":false,"favourites_count":304,"description":"Texas Tech University \r\nPersonal Financial Planning Undergraduate","created_at":"Wed Aug 03 02:24:45 +0000 2011","is_translator":false,"profile_background_image_url_https":"https:\/\/pbs.twimg.com\/profile_background_images\/625129012\/classic-rock.jpg","protected":false,"screen_name":"ShawnTMiles","id_str":"347613207","profile_link_color":"0084B4","id":347613207,"geo_enabled":false,"profile_background_color":"000000","lang":"en","profile_sidebar_border_color":"C0DEED","profile_text_color":"333333","verified":false,"profile_image_url":"http:\/\/pbs.twimg.com\/profile_images\/497799795361079296\/dCapztJV_normal.jpeg","time_zone":"Central Time (US & Canada)","url":null,"contributors_enabled":false,"profile_background_tile":true,"profile_banner_url":"https:\/\/pbs.twimg.com\/profile_banners\/347613207\/1374217384","statuses_count":1364,"follow_request_sent":null,"followers_count":226,"profile_use_background_image":true,"default_profile":false,"following":null,"name":"Shawn Miles","location":null,"profile_sidebar_fill_color":"DDEEF6","notifications":null}}