{"created_at":"Sat Apr 02 02:43:14 +0000 2016","id":716093603454431233,"id_str":"716093603454431233","text":"RT @ClarkLammert35: Texas Tech athletic programs are on the rise across the board, big win for Softball! #WreckEm","source":"\u003ca href=\"http:\/\/twitter.com\/download\/iphone\" rel=\"nofollow\"\u003eTwitter for iPhone\u003c\/a\u003e","truncated":false,"in_reply_to_status_id":null,"in_reply_to_status_id_str":null,"in_reply_to_user_id":null,"in_reply_to_user_id_str":null,"in_reply_to_screen_name":null,"user":{"id":247502316,"id_str":"247502316","name":"B-EEEZY","screen_name":"BrittSquadd_","location":"Chicago, IL \u2708\ufe0f Lubbock, TX","url":null,"description":"I field ground balls for a living~Wreckem \u2022Texas Tech Softball 17' \u2022Instagram\u2022beeez_in_the_trapp SW","protected":false,"verified":false,"followers_count":1033,"friends_count":742,"listed_count":4,"favourites_count":17269,"statuses_count":33283,"created_at":"Fri Feb 04 23:01:45 +0000 2011","utc_offset":-21600,"time_zone":"Mountain Time (US & Canada)","geo_enabled":true,"lang":"en","contributors_enabled":false,"is_translator":false,"profile_background_color":"131516","profile_background_image_url":"http:\/\/pbs.twimg.com\/profile_background_images\/477271655106887680\/eVcIW3Kb.png","profile_background_image_url_https":"https:\/\/pbs.twimg.com\/profile_background_images\/477271655106887680\/eVcIW3Kb.png","profile_background_tile":true,"profile_link_color":"009999","profile_sidebar_border_color":"FFFFFF","profile_sidebar_fill_color":"EFEFEF","profile_text_color":"333333","profile_use_background_image":true,"profile_image_url":"http:\/\/pbs.twimg.com\/profile_images\/710208491030319108\/rCOp44EX_normal.jpg","profile_image_url_https":"https:\/\/pbs.twimg.com\/profile_images\/710208491030319108\/rCOp44EX_normal.jpg","profile_banner_url":"https:\/\/pbs.twimg.com\/profile_banners\/247502316\/1459354837","default_profile":false,"default_profile_image":false,"following":null,"follow_request_sent":null,"notifications":null},"geo":null,"coordinates":null,"place":null,"contributors":null,"retweeted_status":{"created_at":"Sat Apr 02 02:13:50 +0000 2016","id":716086205553594368,"id_str":"716086205553594368","text":"Texas Tech athletic programs are on the rise across the board, big win for Softball! #WreckEm","source":"\u003ca href=\"http:\/\/twitter.com\/download\/iphone\" rel=\"nofollow\"\u003eTwitter for iPhone\u003c\/a\u003e","truncated":false,"in_reply_to_status_id":null,"in_reply_to_status_id_str":null,"in_reply_to_user_id":null,"in_reply_to_user_id_str":null,"in_reply_to_screen_name":null,"user":{"id":50117490,"id_str":"50117490","name":"Clark Lammert","screen_name":"ClarkLammert35","location":"Lubbock, TX","url":"http:\/\/TexasTech.com","description":"Membership Coordinator for @RedRaiderClub | Former Big 12 Athlete | Saved by God's grace | Email: clark.lammert@ttu.edu | Tweets are mine not Tech's |","protected":false,"verified":false,"followers_count":1477,"friends_count":500,"listed_count":15,"favourites_count":1683,"statuses_count":4586,"created_at":"Tue Jun 23 22:04:22 +0000 2009","utc_offset":-18000,"time_zone":"Central Time (US & Canada)","geo_enabled":false,"lang":"en","contributors_enabled":false,"is_translator":false,"profile_background_color":"000000","profile_background_image_url":"http:\/\/pbs.twimg.com\/profile_background_images\/20279331\/mqnewyorkmadness.br.jpg","profile_background_image_url_https":"https:\/\/pbs.twimg.com\/profile_background_images\/20279331\/mqnewyorkmadness.br.jpg","profile_background_tile":false,"profile_link_color":"B6B6B9","profile_sidebar_border_color":"000000","profile_sidebar_fill_color":"616161","profile_text_color":"000000","profile_use_background_image":true,"profile_image_url":"http:\/\/pbs.twimg.com\/profile_images\/701638137668202496\/jo3taf97_normal.jpg","profile_image_url_https":"https:\/\/pbs.twimg.com\/profile_images\/701638137668202496\/jo3taf97_normal.jpg","profile_banner_url":"https:\/\/pbs.twimg.com\/profile_banners\/50117490\/1456118543","default_profile":false,"default_profile_image":false,"following":null,"follow_request_sent":null,"notifications":null},"geo":null,"coordinates":null,"place":null,"contributors":null,"is_quote_status":false,"retweet_count":1,"favorite_count":8,"entities":{"hashtags":[{"text":"WreckEm","indices":[85,93]}],"urls":[],"user_mentions":[],"symbols":[]},"favorited":false,"retweeted":false,"filter_level":"low","lang":"en"},"is_quote_status":false,"retweet_count":0,"favorite_count":0,"entities":{"hashtags":[{"text":"WreckEm","indices":[105,113]}],"urls":[],"user_mentions":[{"screen_name":"ClarkLammert35","name":"Clark Lammert","id":50117490,"id_str":"50117490","indices":[3,18]}],"symbols":[]},"favorited":false,"retweeted":false,"filter_level":"low","lang":"en","timestamp_ms":"1459564994096"}