{"total_sentiment_rank":1.0,"in_reply_to_status_id_str":null,"in_reply_to_status_id":null,"emojiList":null,"created_at":"Thu Apr 21 15:43:44 +0000 2016","in_reply_to_user_id_str":null,"source":"<a href=\"http:\/\/twitter.com\" rel=\"nofollow\">Twitter Web Client<\/a>","retweet_count":0,"retweeted":false,"geo":null,"filter_level":"low","in_reply_to_screen_name":null,"is_quote_status":false,"id_str":"723175392471699456","text_sentiment_rank":1.0,"in_reply_to_user_id":null,"favorite_count":0,"id":723175392471699456,"text":"Coming up on @newschannelnine Midday -- #Volkswagen settlement, Hamilton Co. Shooting investigation and #presidentialelection update.","place":{"country_code":"US","country":"United States","full_name":"Chattanooga, TN","bounding_box":{"coordinates":[[[-85.404424,34.983674],[-85.404424,35.200235],[-85.080704,35.200235],[-85.080704,34.983674]]],"type":"Polygon"},"place_type":"city","name":"Chattanooga","attributes":{},"id":"3b3916ee31cfc9e6","url":"https:\/\/api.twitter.com\/1.1\/geo\/id\/3b3916ee31cfc9e6.json"},"lang":"en","favorited":false,"emoji_sentiment_rank_str":null,"coordinates":null,"truncated":false,"timestamp_ms":"1461253424171","entities":{"urls":[],"hashtags":[{"indices":[40,51],"text":"Volkswagen"},{"indices":[104,125],"text":"presidentialelection"}],"user_mentions":[{"indices":[13,29],"screen_name":"newschannelnine","id_str":"15741370","name":"WTVC NewsChannel 9","id":15741370}],"symbols":[]},"total_sentiment_rank_str":"1.0","text_sentiment_rank_str":"1.0","contributors":null,"emoji_sentiment_rank":null,"user":{"utc_offset":null,"friends_count":2379,"profile_image_url_https":"https:\/\/pbs.twimg.com\/profile_images\/705721467271512064\/vcg0EfU2_normal.jpg","listed_count":67,"profile_background_image_url":"http:\/\/pbs.twimg.com\/profile_background_images\/444187785130283008\/n6G4mNf4.jpeg","default_profile_image":false,"favourites_count":5958,"description":"Morning\/Noon Anchor at WTVC Newschannel 9, motivational speaker, Sylacauga, AL native, University of Montevallo grad, news lover. RT aren't endorsements","created_at":"Mon Jul 15 19:01:27 +0000 2013","is_translator":false,"profile_background_image_url_https":"https:\/\/pbs.twimg.com\/profile_background_images\/444187785130283008\/n6G4mNf4.jpeg","protected":false,"screen_name":"gfunderburgNC9","id_str":"1596548827","profile_link_color":"0099B9","id":1596548827,"geo_enabled":true,"profile_background_color":"0099B9","lang":"en","profile_sidebar_border_color":"FFFFFF","profile_text_color":"3C3940","verified":true,"profile_image_url":"http:\/\/pbs.twimg.com\/profile_images\/705721467271512064\/vcg0EfU2_normal.jpg","time_zone":null,"url":"http:\/\/www.newschannel9.com\/","contributors_enabled":false,"profile_background_tile":true,"profile_banner_url":"https:\/\/pbs.twimg.com\/profile_banners\/1596548827\/1398444460","statuses_count":14006,"follow_request_sent":null,"followers_count":2663,"profile_use_background_image":true,"default_profile":false,"following":null,"name":"Greg Funderburg","location":"Chattanooga, TN","profile_sidebar_fill_color":"95E8EC","notifications":null}}