{"total_sentiment_rank":3.0,"in_reply_to_status_id_str":"723173004293857280","in_reply_to_status_id":723173004293857280,"emojiList":[{"code":"1F602","alias":"joy","tags":["face"," joy"," laugh"," person"," tear"]}],"created_at":"Thu Apr 21 15:39:22 +0000 2016","in_reply_to_user_id_str":"700958311","source":"<a href=\"http:\/\/twitter.com\/download\/iphone\" rel=\"nofollow\">Twitter for iPhone<\/a>","retweet_count":0,"retweeted":false,"geo":null,"filter_level":"low","in_reply_to_screen_name":"number1feeling","is_quote_status":false,"id_str":"723174294038142976","text_sentiment_rank":3.0,"in_reply_to_user_id":700958311,"favorite_count":0,"id":723174294038142976,"text":"@number1feeling You're right ...a very good laugh 😂😂😂😂","place":{"country_code":"US","country":"United States","full_name":"Quantico Base, VA","bounding_box":{"coordinates":[[[-77.361287,38.488805],[-77.361287,38.546631],[-77.282804,38.546631],[-77.282804,38.488805]]],"type":"Polygon"},"place_type":"city","name":"Quantico Base","attributes":{},"id":"0100ce76203579a0","url":"https:\/\/api.twitter.com\/1.1\/geo\/id\/0100ce76203579a0.json"},"lang":"en","favorited":false,"emoji_sentiment_rank_str":"3.0","coordinates":null,"truncated":false,"timestamp_ms":"1461253162284","entities":{"urls":[],"hashtags":[],"user_mentions":[{"indices":[0,15],"screen_name":"number1feeling","id_str":"700958311","name":"KaNegress Pavela","id":700958311}],"symbols":[]},"total_sentiment_rank_str":"3.0","text_sentiment_rank_str":"3.0","contributors":null,"emoji_sentiment_rank":3.0,"user":{"utc_offset":null,"friends_count":197,"profile_image_url_https":"https:\/\/pbs.twimg.com\/profile_images\/3668510132\/78d11cb7dc30d2cf1185cce223be4b48_normal.jpeg","listed_count":4,"profile_background_image_url":"http:\/\/abs.twimg.com\/images\/themes\/theme1\/bg.png","default_profile_image":false,"favourites_count":33759,"description":null,"created_at":"Thu May 07 14:00:18 +0000 2009","is_translator":false,"profile_background_image_url_https":"https:\/\/abs.twimg.com\/images\/themes\/theme1\/bg.png","protected":false,"screen_name":"Brejal","id_str":"38435138","profile_link_color":"0084B4","id":38435138,"geo_enabled":true,"profile_background_color":"C0DEED","lang":"en","profile_sidebar_border_color":"C0DEED","profile_text_color":"333333","verified":false,"profile_image_url":"http:\/\/pbs.twimg.com\/profile_images\/3668510132\/78d11cb7dc30d2cf1185cce223be4b48_normal.jpeg","time_zone":null,"url":null,"contributors_enabled":false,"profile_background_tile":false,"statuses_count":18364,"follow_request_sent":null,"followers_count":159,"profile_use_background_image":true,"default_profile":true,"following":null,"name":"Audrey Herring","location":null,"profile_sidebar_fill_color":"DDEEF6","notifications":null}}