{"total_sentiment_rank":2.0,"in_reply_to_status_id_str":null,"in_reply_to_status_id":null,"emojiList":null,"created_at":"Thu Apr 21 15:47:11 +0000 2016","in_reply_to_user_id_str":null,"source":"<a href=\"http:\/\/www.tweetmyjobs.com\" rel=\"nofollow\">TweetMyJOBS<\/a>","retweet_count":0,"retweeted":false,"geo":{"coordinates":[34.9190189,-81.8442934],"type":"Point"},"filter_level":"low","in_reply_to_screen_name":null,"is_quote_status":false,"id_str":"723176264127770628","text_sentiment_rank":2.0,"in_reply_to_user_id":null,"favorite_count":0,"id":723176264127770628,"text":"Interested in a #Accounting #job near #SPARTANBURG, SC? This could be a great fit: https:\/\/t.co\/xVEOjOyklA #Hiring #CareerArc","place":{"country_code":"US","country":"United States","full_name":"South Carolina, USA","bounding_box":{"coordinates":[[[-83.353955,32.04683],[-83.353955,35.215449],[-78.499301,35.215449],[-78.499301,32.04683]]],"type":"Polygon"},"place_type":"admin","name":"South Carolina","attributes":{},"id":"6057f1e35bcc6c20","url":"https:\/\/api.twitter.com\/1.1\/geo\/id\/6057f1e35bcc6c20.json"},"lang":"en","favorited":false,"possibly_sensitive":false,"emoji_sentiment_rank_str":null,"coordinates":{"coordinates":[-81.8442934,34.9190189],"type":"Point"},"truncated":false,"timestamp_ms":"1461253631990","entities":{"urls":[{"display_url":"bit.ly\/1ZKtI9N","indices":[83,106],"expanded_url":"http:\/\/bit.ly\/1ZKtI9N","url":"https:\/\/t.co\/xVEOjOyklA"}],"hashtags":[{"indices":[16,27],"text":"Accounting"},{"indices":[28,32],"text":"job"},{"indices":[38,50],"text":"SPARTANBURG"},{"indices":[107,114],"text":"Hiring"},{"indices":[115,125],"text":"CareerArc"}],"user_mentions":[],"symbols":[]},"total_sentiment_rank_str":"2.0","text_sentiment_rank_str":"2.0","contributors":null,"emoji_sentiment_rank":null,"user":{"utc_offset":-25200,"friends_count":284,"profile_image_url_https":"https:\/\/pbs.twimg.com\/profile_images\/717205885303595008\/0uK9gzWg_normal.jpg","listed_count":12,"profile_background_image_url":"http:\/\/pbs.twimg.com\/profile_background_images\/315316425\/Twitter-BG_2_bg-image.jpg","default_profile_image":false,"favourites_count":0,"description":"Follow this account for geo-targeted Accounting job tweets in South Carolina Non-Metro. Need help? Tweet us at @CareerArc!","created_at":"Tue Jun 21 21:59:00 +0000 2011","is_translator":false,"profile_background_image_url_https":"https:\/\/pbs.twimg.com\/profile_background_images\/315316425\/Twitter-BG_2_bg-image.jpg","protected":false,"screen_name":"tmj_SC_ACCT","id_str":"321633387","profile_link_color":"4A913C","id":321633387,"geo_enabled":true,"profile_background_color":"253956","lang":"en","profile_sidebar_border_color":"C0DEED","profile_text_color":"333333","verified":false,"profile_image_url":"http:\/\/pbs.twimg.com\/profile_images\/717205885303595008\/0uK9gzWg_normal.jpg","time_zone":"Pacific Time (US & Canada)","url":"http:\/\/www.careerarc.com\/job-seeker","contributors_enabled":false,"profile_background_tile":false,"profile_banner_url":"https:\/\/pbs.twimg.com\/profile_banners\/321633387\/1459830185","statuses_count":16,"follow_request_sent":null,"followers_count":307,"profile_use_background_image":true,"default_profile":false,"following":null,"name":"S Carolina Acct Jobs","location":"South Carolina Non-Metro","profile_sidebar_fill_color":"DDEEF6","notifications":null}}