{"total_sentiment_rank":2.0,"in_reply_to_status_id_str":null,"in_reply_to_status_id":null,"emojiList":null,"created_at":"Fri Feb 12 02:13:39 +0000 2016","in_reply_to_user_id_str":null,"source":"<a href=\"https:\/\/about.twitter.com\/products\/tweetdeck\" rel=\"nofollow\">TweetDeck<\/a>","retweet_count":0,"retweeted":false,"geo":null,"filter_level":"low","in_reply_to_screen_name":null,"is_quote_status":true,"id_str":"697966765410689024","text_sentiment_rank":2.0,"in_reply_to_user_id":null,"favorite_count":0,"id":697966765410689024,"text":"#WreckEm  https:\/\/t.co\/XeesKmaRnk","place":null,"lang":"und","favorited":false,"possibly_sensitive":false,"emoji_sentiment_rank_str":null,"coordinates":null,"truncated":false,"timestamp_ms":"1455243219126","entities":{"urls":[{"display_url":"twitter.com\/TexasTechSocce\u2026","indices":[10,33],"expanded_url":"https:\/\/twitter.com\/TexasTechSoccer\/status\/697966573374418944","url":"https:\/\/t.co\/XeesKmaRnk"}],"hashtags":[{"indices":[0,8],"text":"WreckEm"}],"user_mentions":[],"symbols":[]},"total_sentiment_rank_str":"2.0","text_sentiment_rank_str":"2.0","contributors":null,"emoji_sentiment_rank":null,"user":{"utc_offset":-21600,"friends_count":1574,"profile_image_url_https":"https:\/\/pbs.twimg.com\/profile_images\/533729313019813888\/FTHgsXrZ_normal.jpeg","listed_count":2,"profile_background_image_url":"http:\/\/abs.twimg.com\/images\/themes\/theme14\/bg.gif","default_profile_image":false,"favourites_count":539,"description":"Juanito Fútbol. Started from the border, now we here. LET'S KICK IT!","created_at":"Sun Dec 09 04:53:51 +0000 2012","is_translator":false,"profile_background_image_url_https":"https:\/\/abs.twimg.com\/images\/themes\/theme14\/bg.gif","protected":false,"screen_name":"juanitofutbol","id_str":"998603437","profile_link_color":"CDA766","id":998603437,"geo_enabled":false,"profile_background_color":"000000","lang":"en","profile_sidebar_border_color":"000000","profile_text_color":"000000","verified":false,"profile_image_url":"http:\/\/pbs.twimg.com\/profile_images\/533729313019813888\/FTHgsXrZ_normal.jpeg","time_zone":"Central Time (US & Canada)","url":null,"contributors_enabled":false,"profile_background_tile":false,"profile_banner_url":"https:\/\/pbs.twimg.com\/profile_banners\/998603437\/1410393696","statuses_count":2952,"follow_request_sent":null,"followers_count":455,"profile_use_background_image":false,"default_profile":false,"following":null,"name":"Juanito Fútbol®","location":"Texas Forever","profile_sidebar_fill_color":"000000","notifications":null}}