{"total_sentiment_rank":2.0,"in_reply_to_status_id_str":"723005183916036097","in_reply_to_status_id":723005183916036097,"emojiList":[{"code":"1F602","alias":"joy","tags":["face"," joy"," laugh"," person"," tear"]}],"created_at":"Thu Apr 21 05:10:08 +0000 2016","in_reply_to_user_id_str":"43273187","source":"<a href=\"http:\/\/twitter.com\/download\/iphone\" rel=\"nofollow\">Twitter for iPhone<\/a>","retweet_count":0,"retweeted":false,"geo":null,"filter_level":"low","in_reply_to_screen_name":"christianngomez","is_quote_status":false,"id_str":"723015942603599872","text_sentiment_rank":1.0,"in_reply_to_user_id":43273187,"favorite_count":0,"id":723015942603599872,"text":"@christianngomez @rjoy1919 @sxthrollins No, it's Karole. 😂","place":{"country_code":"US","country":"United States","full_name":"Berkeley, CA","bounding_box":{"coordinates":[[[-122.324818,37.845953],[-122.324818,37.905738],[-122.234225,37.905738],[-122.234225,37.845953]]],"type":"Polygon"},"place_type":"city","name":"Berkeley","attributes":{},"id":"5ef5b7f391e30aff","url":"https:\/\/api.twitter.com\/1.1\/geo\/id\/5ef5b7f391e30aff.json"},"lang":"en","favorited":false,"emoji_sentiment_rank_str":"3.0","coordinates":null,"truncated":false,"timestamp_ms":"1461215408360","entities":{"urls":[],"hashtags":[],"user_mentions":[{"indices":[0,16],"screen_name":"christianngomez","id_str":"43273187","name":"CG","id":43273187},{"indices":[17,26],"screen_name":"rjoy1919","id_str":"2764461268","name":"大好き","id":2764461268},{"indices":[27,39],"screen_name":"sxthrollins","id_str":"2318117408","name":"∙ :. . ∙ .∙","id":2318117408}],"symbols":[]},"total_sentiment_rank_str":"2.0","text_sentiment_rank_str":"1.0","contributors":null,"emoji_sentiment_rank":3.0,"user":{"utc_offset":-25200,"friends_count":761,"profile_image_url_https":"https:\/\/pbs.twimg.com\/profile_images\/714567385336954880\/9yvM16SH_normal.jpg","listed_count":8,"profile_background_image_url":"http:\/\/pbs.twimg.com\/profile_background_images\/673647812\/3c747fd6205be0f624b09dabe50d1a4f.jpeg","default_profile_image":false,"favourites_count":11155,"description":"20. Cal Golden Bear. #BernieSanders2016","created_at":"Sat Jul 31 16:01:37 +0000 2010","is_translator":false,"profile_background_image_url_https":"https:\/\/pbs.twimg.com\/profile_background_images\/673647812\/3c747fd6205be0f624b09dabe50d1a4f.jpeg","protected":false,"screen_name":"KellyAlbers15","id_str":"173157046","profile_link_color":"1CABB0","id":173157046,"geo_enabled":true,"profile_background_color":"050505","lang":"en","profile_sidebar_border_color":"FFFFFF","profile_text_color":"28E0E0","verified":false,"profile_image_url":"http:\/\/pbs.twimg.com\/profile_images\/714567385336954880\/9yvM16SH_normal.jpg","time_zone":"Pacific Time (US & Canada)","url":"http:\/\/m.youtube.com\/user\/JKBeauty08","contributors_enabled":false,"profile_background_tile":true,"profile_banner_url":"https:\/\/pbs.twimg.com\/profile_banners\/173157046\/1458109501","statuses_count":40126,"follow_request_sent":null,"followers_count":844,"profile_use_background_image":true,"default_profile":false,"following":null,"name":"Kelly Albers","location":"Berkeley, California","profile_sidebar_fill_color":"A0C5C7","notifications":null}}