{"total_sentiment_rank":2.5,"quoted_status":{"extended_entities":{"media":[{"display_url":"pic.twitter.com\/CnNWE1mPU1","indices":[104,127],"sizes":{"small":{"w":340,"h":453,"resize":"fit"},"large":{"w":1024,"h":1365,"resize":"fit"},"thumb":{"w":150,"h":150,"resize":"crop"},"medium":{"w":600,"h":800,"resize":"fit"}},"id_str":"723015457335173120","expanded_url":"http:\/\/twitter.com\/eliolmos25\/status\/723015477631426561\/photo\/1","media_url_https":"https:\/\/pbs.twimg.com\/media\/Cgiquk2UYAAMbwx.jpg","id":723015457335173120,"type":"photo","media_url":"http:\/\/pbs.twimg.com\/media\/Cgiquk2UYAAMbwx.jpg","url":"https:\/\/t.co\/CnNWE1mPU1"},{"display_url":"pic.twitter.com\/CnNWE1mPU1","indices":[104,127],"sizes":{"small":{"w":340,"h":115,"resize":"fit"},"large":{"w":750,"h":253,"resize":"fit"},"thumb":{"w":150,"h":150,"resize":"crop"},"medium":{"w":600,"h":202,"resize":"fit"}},"id_str":"723015457339383808","expanded_url":"http:\/\/twitter.com\/eliolmos25\/status\/723015477631426561\/photo\/1","media_url_https":"https:\/\/pbs.twimg.com\/media\/Cgiquk3UoAAYQCP.jpg","id":723015457339383808,"type":"photo","media_url":"http:\/\/pbs.twimg.com\/media\/Cgiquk3UoAAYQCP.jpg","url":"https:\/\/t.co\/CnNWE1mPU1"}]},"in_reply_to_status_id_str":null,"in_reply_to_status_id":null,"created_at":"Thu Apr 21 05:08:17 +0000 2016","in_reply_to_user_id_str":null,"source":"<a href=\"http:\/\/twitter.com\/download\/iphone\" rel=\"nofollow\">Twitter for iPhone<\/a>","retweet_count":0,"retweeted":false,"geo":null,"filter_level":"low","in_reply_to_screen_name":null,"is_quote_status":false,"id_str":"723015477631426561","in_reply_to_user_id":null,"favorite_count":0,"id":723015477631426561,"text":"I didn't know I would get a $24,000 scholarship to ASU for just filling out \"information pamphlets\" 🐸☕️ https:\/\/t.co\/CnNWE1mPU1","place":null,"lang":"en","favorited":false,"possibly_sensitive":false,"coordinates":null,"truncated":false,"entities":{"urls":[],"hashtags":[],"media":[{"display_url":"pic.twitter.com\/CnNWE1mPU1","indices":[104,127],"sizes":{"small":{"w":340,"h":453,"resize":"fit"},"large":{"w":1024,"h":1365,"resize":"fit"},"thumb":{"w":150,"h":150,"resize":"crop"},"medium":{"w":600,"h":800,"resize":"fit"}},"id_str":"723015457335173120","expanded_url":"http:\/\/twitter.com\/eliolmos25\/status\/723015477631426561\/photo\/1","media_url_https":"https:\/\/pbs.twimg.com\/media\/Cgiquk2UYAAMbwx.jpg","id":723015457335173120,"type":"photo","media_url":"http:\/\/pbs.twimg.com\/media\/Cgiquk2UYAAMbwx.jpg","url":"https:\/\/t.co\/CnNWE1mPU1"}],"user_mentions":[],"symbols":[]},"contributors":null,"user":{"utc_offset":null,"friends_count":225,"profile_image_url_https":"https:\/\/pbs.twimg.com\/profile_images\/722525427420389376\/-yc_e29u_normal.jpg","listed_count":2,"profile_background_image_url":"http:\/\/abs.twimg.com\/images\/themes\/theme1\/bg.png","default_profile_image":false,"favourites_count":2342,"description":"I'm in the door, now it's up to me to make the best out of the opportunity #forksup","created_at":"Sun Jun 02 05:58:34 +0000 2013","is_translator":false,"profile_background_image_url_https":"https:\/\/abs.twimg.com\/images\/themes\/theme1\/bg.png","protected":false,"screen_name":"eliolmos25","id_str":"1476514724","profile_link_color":"0084B4","id":1476514724,"geo_enabled":true,"profile_background_color":"C0DEED","lang":"en","profile_sidebar_border_color":"C0DEED","profile_text_color":"333333","verified":false,"profile_image_url":"http:\/\/pbs.twimg.com\/profile_images\/722525427420389376\/-yc_e29u_normal.jpg","time_zone":null,"url":null,"contributors_enabled":false,"profile_background_tile":false,"profile_banner_url":"https:\/\/pbs.twimg.com\/profile_banners\/1476514724\/1460348926","statuses_count":3713,"follow_request_sent":null,"followers_count":355,"profile_use_background_image":true,"default_profile":true,"following":null,"name":"∑ ﾚ ⅰ","location":"Superior, AZ~~WR~~ 2nd base~~","profile_sidebar_fill_color":"DDEEF6","notifications":null}},"in_reply_to_status_id_str":null,"in_reply_to_status_id":null,"emojiList":[{"code":"1F44C","alias":"ok_hand","tags":["body"," hand"," ok"," person"]},{"code":"1F4AF","alias":"100.0","tags":["100"," full"," hundred"," office"," score"," symbol"]}],"created_at":"Thu Apr 21 05:16:52 +0000 2016","in_reply_to_user_id_str":null,"source":"<a href=\"http:\/\/twitter.com\/download\/android\" rel=\"nofollow\">Twitter for Android<\/a>","quoted_status_id":723015477631426561,"retweet_count":0,"retweeted":false,"geo":null,"filter_level":"low","in_reply_to_screen_name":null,"is_quote_status":true,"id_str":"723017639484903424","text_sentiment_rank":2.6666666666666665,"in_reply_to_user_id":null,"favorite_count":0,"id":723017639484903424,"text":"You deserved it Eli! You work hard for this and continue working hard. Very proud of you bro 👌💯 Congrats! https:\/\/t.co\/lidjQY4Y3R","place":{"country_code":"US","country":"United States","full_name":"Superior, AZ","bounding_box":{"coordinates":[[[-111.122426,33.273478],[-111.122426,33.300264],[-111.092327,33.300264],[-111.092327,33.273478]]],"type":"Polygon"},"place_type":"city","name":"Superior","attributes":{},"id":"a06c4ac3ba741a05","url":"https:\/\/api.twitter.com\/1.1\/geo\/id\/a06c4ac3ba741a05.json"},"lang":"en","favorited":false,"possibly_sensitive":false,"emoji_sentiment_rank_str":"2.3333333333333335","coordinates":null,"truncated":false,"timestamp_ms":"1461215812928","entities":{"urls":[{"display_url":"twitter.com\/eliolmos25\/sta\u2026","indices":[106,129],"expanded_url":"https:\/\/twitter.com\/eliolmos25\/status\/723015477631426561","url":"https:\/\/t.co\/lidjQY4Y3R"}],"hashtags":[],"user_mentions":[],"symbols":[]},"total_sentiment_rank_str":"2.5","text_sentiment_rank_str":"2.6666666666666665","quoted_status_id_str":"723015477631426561","contributors":null,"emoji_sentiment_rank":2.3333333333333335,"user":{"utc_offset":null,"friends_count":151,"profile_image_url_https":"https:\/\/pbs.twimg.com\/profile_images\/714674401514557444\/FmUX9rXn_normal.jpg","listed_count":0,"profile_background_image_url":"http:\/\/abs.twimg.com\/images\/themes\/theme10\/bg.gif","default_profile_image":false,"favourites_count":2189,"description":"Happily taken by my dream guy and the best boyfriend @jakey_sotelo74 ❤ Fam is the key to happiness❤","created_at":"Tue Jul 23 21:28:48 +0000 2013","is_translator":false,"profile_background_image_url_https":"https:\/\/abs.twimg.com\/images\/themes\/theme10\/bg.gif","protected":false,"screen_name":"gabby_kipp","id_str":"1616149148","profile_link_color":"F5ABB5","id":1616149148,"geo_enabled":true,"profile_background_color":"642D8B","lang":"en","profile_sidebar_border_color":"C0DEED","profile_text_color":"333333","verified":false,"profile_image_url":"http:\/\/pbs.twimg.com\/profile_images\/714674401514557444\/FmUX9rXn_normal.jpg","time_zone":null,"url":null,"contributors_enabled":false,"profile_background_tile":false,"profile_banner_url":"https:\/\/pbs.twimg.com\/profile_banners\/1616149148\/1459226628","statuses_count":2295,"follow_request_sent":null,"followers_count":164,"profile_use_background_image":true,"default_profile":false,"following":null,"name":"♡Gabriella♡","location":"Superior, AZ","profile_sidebar_fill_color":"DDEEF6","notifications":null}}