{"extended_entities":{"media":[{"display_url":"pic.twitter.com\/V1W4B6Df3R","indices":[95,118],"sizes":{"small":{"w":340,"h":191,"resize":"fit"},"large":{"w":1024,"h":576,"resize":"fit"},"thumb":{"w":150,"h":150,"resize":"crop"},"medium":{"w":600,"h":338,"resize":"fit"}},"id_str":"717084394821791744","expanded_url":"http:\/\/twitter.com\/KTTZ\/status\/717084781310119936\/video\/1","media_url_https":"https:\/\/pbs.twimg.com\/ext_tw_video_thumb\/717084394821791744\/pu\/img\/zVLXjO4D5pE04y-A.jpg","id":717084394821791744,"type":"video","media_url":"http:\/\/pbs.twimg.com\/ext_tw_video_thumb\/717084394821791744\/pu\/img\/zVLXjO4D5pE04y-A.jpg","url":"https:\/\/t.co\/V1W4B6Df3R","video_info":{"aspect_ratio":[16,9],"duration_millis":15015,"variants":[{"content_type":"video\/mp4","bitrate":832000,"url":"https:\/\/video.twimg.com\/ext_tw_video\/717084394821791744\/pu\/vid\/640x360\/Swd3HToumAVW2plz.mp4"},{"content_type":"video\/mp4","bitrate":2176000,"url":"https:\/\/video.twimg.com\/ext_tw_video\/717084394821791744\/pu\/vid\/1280x720\/O9Mxstid8ln0_FDR.mp4"},{"content_type":"video\/mp4","bitrate":320000,"url":"https:\/\/video.twimg.com\/ext_tw_video\/717084394821791744\/pu\/vid\/320x180\/hWDga2NpNiiNIKRe.mp4"},{"content_type":"application\/x-mpegURL","url":"https:\/\/video.twimg.com\/ext_tw_video\/717084394821791744\/pu\/pl\/MzhOMBoN606qJy4z.m3u8"},{"content_type":"application\/dash+xml","url":"https:\/\/video.twimg.com\/ext_tw_video\/717084394821791744\/pu\/pl\/MzhOMBoN606qJy4z.mpd"}]}}]},"total_sentiment_rank":1.6666666666666667,"in_reply_to_status_id_str":null,"in_reply_to_status_id":null,"emojiList":null,"created_at":"Mon Apr 04 20:21:49 +0000 2016","in_reply_to_user_id_str":null,"source":"<a href=\"http:\/\/twitter.com\" rel=\"nofollow\">Twitter Web Client<\/a>","retweet_count":0,"retweeted":false,"geo":null,"filter_level":"low","in_reply_to_screen_name":null,"is_quote_status":false,"id_str":"717084781310119936","text_sentiment_rank":1.6666666666666667,"in_reply_to_user_id":null,"favorite_count":0,"id":717084781310119936,"text":"Watch a new episode of #InsideTexasTech, Thursday @ 7 on Ch. 5, @KTTZ! @TexasTech #MYKTTZ #TTU https:\/\/t.co\/V1W4B6Df3R","place":null,"lang":"en","favorited":false,"possibly_sensitive":false,"emoji_sentiment_rank_str":null,"coordinates":null,"truncated":false,"timestamp_ms":"1459801309312","entities":{"urls":[],"hashtags":[{"indices":[23,39],"text":"InsideTexasTech"},{"indices":[82,89],"text":"MYKTTZ"},{"indices":[90,94],"text":"TTU"}],"media":[{"display_url":"pic.twitter.com\/V1W4B6Df3R","indices":[95,118],"sizes":{"small":{"w":340,"h":191,"resize":"fit"},"large":{"w":1024,"h":576,"resize":"fit"},"thumb":{"w":150,"h":150,"resize":"crop"},"medium":{"w":600,"h":338,"resize":"fit"}},"id_str":"717084394821791744","expanded_url":"http:\/\/twitter.com\/KTTZ\/status\/717084781310119936\/video\/1","media_url_https":"https:\/\/pbs.twimg.com\/ext_tw_video_thumb\/717084394821791744\/pu\/img\/zVLXjO4D5pE04y-A.jpg","id":717084394821791744,"type":"photo","media_url":"http:\/\/pbs.twimg.com\/ext_tw_video_thumb\/717084394821791744\/pu\/img\/zVLXjO4D5pE04y-A.jpg","url":"https:\/\/t.co\/V1W4B6Df3R"}],"user_mentions":[{"indices":[64,69],"screen_name":"KTTZ","id_str":"217544468","name":"TTU Public Media","id":217544468},{"indices":[71,81],"screen_name":"TexasTech","id_str":"14125882","name":"Texas Tech","id":14125882}],"symbols":[]},"total_sentiment_rank_str":"1.6666666666666667","text_sentiment_rank_str":"1.6666666666666667","contributors":null,"emoji_sentiment_rank":null,"user":{"utc_offset":-18000,"friends_count":143,"profile_image_url_https":"https:\/\/pbs.twimg.com\/profile_images\/685505296941252609\/V6cuCgZA_normal.jpg","listed_count":26,"profile_background_image_url":"http:\/\/pbs.twimg.com\/profile_background_images\/173336082\/x9158bbd49bfd9470c03e05ef20d6fdc.png","default_profile_image":false,"favourites_count":100,"description":"Texas Tech Public Broadcasting | KTTZ-TV Channel 5 | KTTZ-FM 89.1","created_at":"Fri Nov 19 20:39:07 +0000 2010","is_translator":false,"profile_background_image_url_https":"https:\/\/pbs.twimg.com\/profile_background_images\/173336082\/x9158bbd49bfd9470c03e05ef20d6fdc.png","protected":false,"screen_name":"KTTZ","id_str":"217544468","profile_link_color":"000000","id":217544468,"geo_enabled":false,"profile_background_color":"131516","lang":"en","profile_sidebar_border_color":"000000","profile_text_color":"597C99","verified":false,"profile_image_url":"http:\/\/pbs.twimg.com\/profile_images\/685505296941252609\/V6cuCgZA_normal.jpg","time_zone":"Central Time (US & Canada)","url":"http:\/\/www.kttz.org","contributors_enabled":false,"profile_background_tile":true,"profile_banner_url":"https:\/\/pbs.twimg.com\/profile_banners\/217544468\/1459433459","statuses_count":1714,"follow_request_sent":null,"followers_count":414,"profile_use_background_image":true,"default_profile":false,"following":null,"name":"TTU Public Media","location":"Lubbock, TX","profile_sidebar_fill_color":"140C0C","notifications":null}}