{"extended_entities":{"media":[{"display_url":"pic.twitter.com\/ltj3S6xbSj","indices":[69,92],"sizes":{"small":{"w":340,"h":604,"resize":"fit"},"large":{"w":640,"h":1136,"resize":"fit"},"thumb":{"w":150,"h":150,"resize":"crop"},"medium":{"w":600,"h":1065,"resize":"fit"}},"id_str":"707688144930385920","expanded_url":"http:\/\/twitter.com\/ericearl18\/status\/707688148805877760\/photo\/1","media_url_https":"https:\/\/pbs.twimg.com\/media\/CdI2nkpUsAAIQH1.jpg","id":707688144930385920,"type":"photo","media_url":"http:\/\/pbs.twimg.com\/media\/CdI2nkpUsAAIQH1.jpg","url":"https:\/\/t.co\/ltj3S6xbSj"}]},"total_sentiment_rank":1.0,"in_reply_to_status_id_str":null,"in_reply_to_status_id":null,"emojiList":null,"created_at":"Wed Mar 09 22:02:57 +0000 2016","in_reply_to_user_id_str":null,"source":"<a href=\"http:\/\/twitter.com\/download\/iphone\" rel=\"nofollow\">Twitter for iPhone<\/a>","retweet_count":0,"retweeted":false,"geo":null,"filter_level":"low","in_reply_to_screen_name":null,"is_quote_status":false,"id_str":"707688148805877760","text_sentiment_rank":1.0,"in_reply_to_user_id":null,"favorite_count":0,"id":707688148805877760,"text":"This is how a true red raider comes out of surgery....#TTU20 #GunsUp https:\/\/t.co\/ltj3S6xbSj","place":null,"lang":"en","favorited":false,"possibly_sensitive":false,"emoji_sentiment_rank_str":null,"coordinates":null,"truncated":false,"timestamp_ms":"1457560977542","entities":{"urls":[],"hashtags":[{"indices":[54,60],"text":"TTU20"},{"indices":[61,68],"text":"GunsUp"}],"media":[{"display_url":"pic.twitter.com\/ltj3S6xbSj","indices":[69,92],"sizes":{"small":{"w":340,"h":604,"resize":"fit"},"large":{"w":640,"h":1136,"resize":"fit"},"thumb":{"w":150,"h":150,"resize":"crop"},"medium":{"w":600,"h":1065,"resize":"fit"}},"id_str":"707688144930385920","expanded_url":"http:\/\/twitter.com\/ericearl18\/status\/707688148805877760\/photo\/1","media_url_https":"https:\/\/pbs.twimg.com\/media\/CdI2nkpUsAAIQH1.jpg","id":707688144930385920,"type":"photo","media_url":"http:\/\/pbs.twimg.com\/media\/CdI2nkpUsAAIQH1.jpg","url":"https:\/\/t.co\/ltj3S6xbSj"}],"user_mentions":[],"symbols":[]},"total_sentiment_rank_str":"1.0","text_sentiment_rank_str":"1.0","contributors":null,"emoji_sentiment_rank":null,"user":{"utc_offset":null,"friends_count":340,"profile_image_url_https":"https:\/\/pbs.twimg.com\/profile_images\/696687547825541122\/ei3SICmp_normal.jpg","listed_count":1,"profile_background_image_url":"http:\/\/abs.twimg.com\/images\/themes\/theme1\/bg.png","default_profile_image":false,"favourites_count":6898,"description":"Dream no little dream. Phil 4:13 #TTU20 #makeamericagreatagain","created_at":"Tue Apr 16 03:28:43 +0000 2013","is_translator":false,"profile_background_image_url_https":"https:\/\/abs.twimg.com\/images\/themes\/theme1\/bg.png","protected":false,"screen_name":"ericearl18","id_str":"1355944652","profile_link_color":"0084B4","id":1355944652,"geo_enabled":false,"profile_background_color":"C0DEED","lang":"en","profile_sidebar_border_color":"C0DEED","profile_text_color":"333333","verified":false,"profile_image_url":"http:\/\/pbs.twimg.com\/profile_images\/696687547825541122\/ei3SICmp_normal.jpg","time_zone":null,"url":"http:\/\/www.hudl.com\/athlete\/2023075\/highlights\/302381407","contributors_enabled":false,"profile_background_tile":false,"profile_banner_url":"https:\/\/pbs.twimg.com\/profile_banners\/1355944652\/1446335806","statuses_count":5025,"follow_request_sent":null,"followers_count":303,"profile_use_background_image":true,"default_profile":true,"following":null,"name":"amERICa","location":"Highland Village, TX","profile_sidebar_fill_color":"DDEEF6","notifications":null}}